{
    "project_name": "BaSyx",
    "project_url": "https://projects.eclipse.org/projects/dt.basyx",
    "status": "Incubating",
    "tech": "Digital Twin",
    "releases": [
        {
            "name": "2.0.0-milestone-02 (JAVA)",
            "url": "https://projects.eclipse.org/projects/dt.basyx/releases/2.0.0-milestone-02-java",
            "date": "2024-03-08"
        },
        {
            "name": "1.5.1 (JAVA)",
            "url": "https://projects.eclipse.org/projects/dt.basyx/releases/1.5.1-java",
            "date": "2024-02-05"
        },
        {
            "name": "1.0.0 (PYTHON)",
            "url": "https://projects.eclipse.org/projects/dt.basyx/releases/1.0.0-python",
            "date": "2023-11-27"
        },
        {
            "name": "0.2.0 (RUST)",
            "url": "https://projects.eclipse.org/projects/dt.basyx/releases/0.2.0-rust",
            "date": "2023-05-31"
        },
        {
            "name": "1.4.0 (JAVA)",
            "url": "https://projects.eclipse.org/projects/dt.basyx/releases/1.4.0-java",
            "date": "2023-04-03"
        },
        {
            "name": "1.3.1 (JAVA)",
            "url": "https://projects.eclipse.org/projects/dt.basyx/releases/1.3.1-java",
            "date": "2023-02-08"
        },
        {
            "name": "1.3.0 (JAVA)",
            "url": "https://projects.eclipse.org/projects/dt.basyx/releases/1.3.0-java",
            "date": "2022-12-15"
        },
        {
            "name": "1.2.0 (JAVA)",
            "url": "https://projects.eclipse.org/projects/dt.basyx/releases/1.2.0-java",
            "date": "2022-07-29"
        },
        {
            "name": "0.2.2 (Python)",
            "url": "https://projects.eclipse.org/projects/dt.basyx/releases/0.2.2-python",
            "date": "2022-06-02"
        },
        {
            "name": "1.1.0 (JAVA)",
            "url": "https://projects.eclipse.org/projects/dt.basyx/releases/1.1.0-java",
            "date": "2022-04-22"
        },
        {
            "name": "1.0.2 (JAVA)",
            "url": "https://projects.eclipse.org/projects/technology.basyx/releases/1.0.2-java",
            "date": "2021-12-15"
        },
        {
            "name": "0.1.0 (RUST)",
            "url": "https://projects.eclipse.org/projects/technology.basyx/releases/0.1.0-rust",
            "date": "2021-11-29"
        },
        {
            "name": "1.0.1 (JAVA)",
            "url": "https://projects.eclipse.org/projects/technology.basyx/releases/1.0.1-java",
            "date": "2021-10-15"
        },
        {
            "name": "1.0.0 (.NET)",
            "url": "https://projects.eclipse.org/projects/technology.basyx/releases/1.0.0-.net",
            "date": "2021-07-06"
        },
        {
            "name": "1.0.0 (JAVA)",
            "url": "https://projects.eclipse.org/projects/technology.basyx/releases/1.0.0-java",
            "date": "2021-03-18"
        },
        {
            "name": "1.0.0 (C++)",
            "url": "https://projects.eclipse.org/projects/technology.basyx/releases/1.0.0-c",
            "date": "2021-01-30"
        }
    ]
}