{
    "project_name": "EE4J",
    "project_url": "https://projects.eclipse.org/projects/ee4j",
    "status": "Mature",
    "tech": "EE4J",
    "releases": [
        {
            "name": "Restructure Jakarta EE Specification Projects",
            "url": "https://projects.eclipse.org/projects/ee4j/reviews/restructure-jakarta-ee-specification-projects-1",
            "date": "2019-07-03"
        },
        {
            "name": "Restructure Jakarta EE Specification Projects",
            "url": "https://projects.eclipse.org/projects/ee4j/reviews/restructure-jakarta-ee-specification-projects-0",
            "date": "2019-06-24"
        },
        {
            "name": "Restructure Jakarta EE Specification Projects",
            "url": "https://projects.eclipse.org/projects/ee4j/reviews/restructure-jakarta-ee-specification-projects",
            "date": "2019-06-17"
        },
        {
            "name": "Top Level Project Creation",
            "url": "https://projects.eclipse.org/projects/ee4j/reviews/top-level-project-creation",
            "date": "2017-10-25"
        }
    ]
}